rpextractsink/__init__.py
rpextractsink/__main__.py
rpextractsink/rpextractsink.py
rpextractsink-1.0.1.dist-info/LICENSE
rpextractsink-1.0.1.dist-info/METADATA
rpextractsink-1.0.1.dist-info/WHEEL
rpextractsink-1.0.1.dist-info/top_level.txt
rpextractsink-1.0.1.dist-info/RECORD
