Metadata-Version: 2.1
Name: rpextractsink
Version: 1.0.1
Summary: 'retropath2 sink generator'
Home-page: https://github.com/brsynth/rpextractsink
Author: 'melchior du lac, thomas duigou, joan hérisson'
Author-email: thomas.duigou@inra.fr
License: MIT
Platform: UNKNOWN
Classifier: Programming Language :: Python :: 3
Classifier: License :: OSI Approved :: MIT License
Classifier: Operating System :: OS Independent
Requires-Python: >=3.5
Requires-Dist: brs-libs
Requires-Dist: cobra (==0.16)
Requires-Dist: timeout-decorator
